orchestrator/__main__.py
orchestrator/timeout.py
orchestrator/xml_reader.py
orchestrator-1.0.dist-info/LICENSE
orchestrator-1.0.dist-info/METADATA
orchestrator-1.0.dist-info/WHEEL
orchestrator-1.0.dist-info/top_level.txt
orchestrator-1.0.dist-info/RECORD
