Metadata-Version: 2.1
Name: orchestrator
Version: 1.0
Summary: Process orchestrator
Home-page: UNKNOWN
Author: Vinogradov D
Author-email: dmitrij.vinogradov@se.com
License: MIT
Platform: UNKNOWN
